fudstop_imps/__init__.py
utils/__init__.py
utils/endpoints.py
fudstop_imps-0.0.4.dist-info/METADATA
fudstop_imps-0.0.4.dist-info/WHEEL
fudstop_imps-0.0.4.dist-info/top_level.txt
fudstop_imps-0.0.4.dist-info/RECORD
