Metadata-Version: 2.1
Name: fudstop_imps
Version: 0.0.4
Summary: Imports for fudstop4 package.
Author: Chuck Dustin
Author-email: chuckdustin12@gmail.com
License: MIT
Classifier: Programming Language :: Python :: 3
Classifier: License :: OSI Approved :: MIT License
Classifier: Operating System :: OS Independent
Requires-Python: >=3.11
